[
    {
        "name": "Chotipat",
        "score": 680000
    },
    {
        "name": "Chotipat",
        "score": 4820
    },
    {
        "name": "Guest",
        "score": 4540
    },
    {
        "name": "1",
        "score": 3340
    },
    {
        "name": "12",
        "score": 2730
    },
    {
        "name": "Guest",
        "score": 2200
    },
    {
        "name": "Guest",
        "score": 1840
    },
    {
        "name": "Chotipat",
        "score": 1100
    },
    {
        "name": "Guest",
        "score": 690
    },
    {
        "name": "Guest",
        "score": 480
    }
]